dp_sqlalchemy_wrapper/__init__.py
dp_sqlalchemy_wrapper/base_config.py
dp_sqlalchemy_wrapper/base_db.py
dp_sqlalchemy_wrapper/declarative_util.py
dp_sqlalchemy_wrapper/json_fill.py
dp_sqlalchemy_wrapper-2.3.0.dist-info/LICENSE
dp_sqlalchemy_wrapper-2.3.0.dist-info/METADATA
dp_sqlalchemy_wrapper-2.3.0.dist-info/WHEEL
dp_sqlalchemy_wrapper-2.3.0.dist-info/top_level.txt
dp_sqlalchemy_wrapper-2.3.0.dist-info/RECORD
