Metadata-Version: 2.1
Name: dp-sqlalchemy-wrapper
Version: 2.3.0
Summary: A slim wrapper around sqlalchemy to simplify database setup and common operations
Home-page: https://github.com/dataPuzzler/dp_sqlalchemy_wrapper
Author: Lukas Seppelfricke
Author-email: data.puzzler@gmail.com
License: UNKNOWN
Keywords: sqlalchemy,wrapper
Platform: UNKNOWN
Classifier: Development Status :: 4 - Beta
Classifier: Intended Audience :: Developers
Classifier: Topic :: Software Development :: Libraries
Classifier: License :: OSI Approved :: BSD License
Classifier: Programming Language :: Python :: 3
Requires-Python: >=3.7, <4
Requires-Dist: sqlalchemy (>=1.4)
Provides-Extra: json_fill
Requires-Dist: dp-json-util (>=2.0) ; extra == 'json_fill'
Provides-Extra: test
